{"version":1,"resource":"vscode-remote://ssh-remote%2Bec2-47-129-240-41.ap-southeast-1.compute.amazonaws.com/home/ubuntu/Pem/package.json","entries":[{"id":"fsZk.json","timestamp":1733493606892},{"id":"uHLH.json","timestamp":1733493642483},{"id":"xXJn.json","timestamp":1733493745057},{"id":"f9yU.json","timestamp":1733651319374},{"id":"4oof.json","timestamp":1733651349529},{"id":"GC2e.json","source":"undoRedo.source","timestamp":1733651359525},{"id":"7eBS.json","source":"undoRedo.source","timestamp":1733651390505},{"id":"gelg.json","timestamp":1733651440839},{"id":"TbVE.json","source":"undoRedo.source","timestamp":1733651462816},{"id":"JgLE.json","timestamp":1733651466174}]}